ckanext/essopendata_theme/__init__.py
ckanext/essopendata_theme/plugin.py
ckanext/essopendata_theme/public/base/activity.css
ckanext/essopendata_theme/public/base/essopendata_theme.css
ckanext/essopendata_theme/public/base/main.css
ckanext/essopendata_theme/public/base/visualize_main.css
ckanext/essopendata_theme/public/base/fonts/cooperblkbt-italic-webfont.woff2
ckanext/essopendata_theme/public/base/fonts/cooperblkbt-regular-webfont.woff2
ckanext/essopendata_theme/public/base/fonts/cooperltbt-bold-webfont.woff2
ckanext/essopendata_theme/public/base/fonts/cooperltbt-bolditalic-webfont.woff2
ckanext/essopendata_theme/public/base/fonts/cooperltbt-italic-webfont.woff2
ckanext/essopendata_theme/public/base/fonts/cooperltbt-regular-webfont.woff2
ckanext/essopendata_theme/public/base/fonts/coopermdbt-italic-webfont.woff2
ckanext/essopendata_theme/public/base/fonts/coopermdbt-regular-webfont.woff2
ckanext/essopendata_theme/public/base/images/Logo_cLogo_esquerra_png_EspaiDadesESS.png
ckanext/essopendata_theme/public/base/images/Logo_centrat_fons_blanc_EspaiDadesESS.png
ckanext/essopendata_theme/public/base/images/Logo_centrat_png_EspaiDadesESS.png
ckanext/essopendata_theme/public/base/images/coopdevs_logo_A_hrz2.png
ckanext/essopendata_theme/public/base/images/essespaidades.svg
ckanext/essopendata_theme/public/base/images/essopendata2.svg
ckanext/essopendata_theme/public/base/images/favicon.ico
ckanext/essopendata_theme/public/base/images/faviconess.ico
ckanext/essopendata_theme/public/base/images/img_capcalera.png
ckanext/essopendata_theme/public/base/images/logo_ajuntamentbcn.svg
ckanext/essopendata_theme/public/base/images/logo_collectivat.png
ckanext/essopendata_theme/public/base/images/logo_coopdevs.png
ckanext/essopendata_theme/public/base/images/logo_coopdevs_white.png
ckanext/essopendata_theme/public/base/images/logo_ibod.png
ckanext/essopendata_theme/public/base/images/logo_xes.png
ckanext/essopendata_theme/templates/base.html
ckanext_essopendata_theme-0.1.3.dist-info/METADATA
ckanext_essopendata_theme-0.1.3.dist-info/WHEEL
ckanext_essopendata_theme-0.1.3.dist-info/entry_points.txt
ckanext_essopendata_theme-0.1.3.dist-info/top_level.txt
ckanext_essopendata_theme-0.1.3.dist-info/RECORD
